{"ts":"2026-06-22T11:14:01+09:00","kospi":{"외국인":{"매도":65335,"매수":50055,"순매수":-15280},"개인":{"매도":84032,"매수":92739,"순매수":8707},"기관":{"매도":51768,"매수":57984,"순매수":6216,"세부":{"금융투자":{"매도":10224,"매수":14513,"순매수":4289},"투신":{"매도":1705,"매수":1286,"순매수":-419},"보험":{"매도":327,"매수":245,"순매수":-83},"사모펀드":{"매도":1480,"매수":1782,"순매수":301},"은행":{"매도":27,"매수":29,"순매수":3},"기타금융":{"매도":70,"매수":26,"순매수":-44},"연기금등":{"매도":37935,"매수":40103,"순매수":2168},"국가/지자체":{"매도":0,"매수":0,"순매수":0}}},"기타법인":{"매도":1644,"매수":2001,"순매수":357}},"kosdaq":{"외국인":{"매도":12926,"매수":14890,"순매수":1963},"개인":{"매도":31902,"매수":28992,"순매수":-2910},"기관":{"매도":3477,"매수":4423,"순매수":946,"세부":{"금융투자":{"매도":2119,"매수":2625,"순매수":507},"투신":{"매도":397,"매수":335,"순매수":-63},"보험":{"매도":18,"매수":27,"순매수":8},"사모펀드":{"매도":370,"매수":681,"순매수":311},"은행":{"매도":0,"매수":0,"순매수":0},"기타금융":{"매도":15,"매수":2,"순매수":-13},"연기금등":{"매도":558,"매수":753,"순매수":195},"국가/지자체":{"매도":0,"매수":0,"순매수":0}}},"기타법인":{"매도":329,"매수":330,"순매수":1}},"index":{"kospi":{"지수":9178.87,"전일대비":126.45,"등락률":1.4},"kosdaq":{"지수":958.88,"전일대비":-7.71,"등락률":-0.8}}}