{"ts":"2026-06-04T13:39:00+09:00","kospi":{"외국인":{"매도":179239,"매수":123172,"순매수":-56068},"개인":{"매도":90798,"매수":132092,"순매수":41294},"기관":{"매도":67799,"매수":81602,"순매수":13803,"세부":{"금융투자":{"매도":17777,"매수":28974,"순매수":11197},"투신":{"매도":3384,"매수":3380,"순매수":-5},"보험":{"매도":667,"매수":549,"순매수":-118},"사모펀드":{"매도":3845,"매수":2970,"순매수":-875},"은행":{"매도":69,"매수":62,"순매수":-7},"기타금융":{"매도":41,"매수":145,"순매수":104},"연기금등":{"매도":42016,"매수":45522,"순매수":3506},"국가/지자체":{"매도":0,"매수":0,"순매수":0}}},"기타법인":{"매도":2202,"매수":3172,"순매수":970}},"kosdaq":{"외국인":{"매도":26292,"매수":26280,"순매수":-11},"개인":{"매도":57353,"매수":54952,"순매수":-2402},"기관":{"매도":6680,"매수":9032,"순매수":2353,"세부":{"금융투자":{"매도":4063,"매수":5320,"순매수":1257},"투신":{"매도":628,"매수":1121,"순매수":493},"보험":{"매도":67,"매수":144,"순매수":77},"사모펀드":{"매도":890,"매수":1165,"순매수":276},"은행":{"매도":1,"매수":4,"순매수":3},"기타금융":{"매도":41,"매수":9,"순매수":-32},"연기금등":{"매도":989,"매수":1270,"순매수":280},"국가/지자체":{"매도":0,"매수":0,"순매수":0}}},"기타법인":{"매도":591,"매수":651,"순매수":60}}}