{"ts":"2026-06-16T14:29:01+09:00","kospi":{"외국인":{"매도":95378,"매수":104678,"순매수":9300},"개인":{"매도":153266,"매수":135635,"순매수":-17630},"기관":{"매도":77280,"매수":85973,"순매수":8693,"세부":{"금융투자":{"매도":17570,"매수":22166,"순매수":4596},"투신":{"매도":11695,"매수":13859,"순매수":2164},"보험":{"매도":1192,"매수":836,"순매수":-356},"사모펀드":{"매도":3341,"매수":5079,"순매수":1738},"은행":{"매도":63,"매수":119,"순매수":55},"기타금융":{"매도":580,"매수":230,"순매수":-350},"연기금등":{"매도":42839,"매수":43684,"순매수":845},"국가/지자체":{"매도":0,"매수":0,"순매수":0}}},"기타법인":{"매도":3083,"매수":2721,"순매수":-362}},"kosdaq":{"외국인":{"매도":22916,"매수":20252,"순매수":-2664},"개인":{"매도":42924,"매수":49584,"순매수":6661},"기관":{"매도":10048,"매수":6197,"순매수":-3851,"세부":{"금융투자":{"매도":4510,"매수":2741,"순매수":-1770},"투신":{"매도":3199,"매수":1287,"순매수":-1912},"보험":{"매도":133,"매수":80,"순매수":-53},"사모펀드":{"매도":1083,"매수":1140,"순매수":57},"은행":{"매도":2,"매수":2,"순매수":1},"기타금융":{"매도":48,"매수":11,"순매수":-37},"연기금등":{"매도":1073,"매수":936,"순매수":-137},"국가/지자체":{"매도":0,"매수":0,"순매수":0}}},"기타법인":{"매도":669,"매수":524,"순매수":-146}},"index":{"kospi":{"지수":8722.73,"전일대비":176.75,"등락률":2.07},"kosdaq":{"지수":1017.63,"전일대비":-16.4,"등락률":-1.59}}}