{"ts":"2026-06-19T10:11:01+09:00","kospi":{"외국인":{"매도":54812,"매수":50050,"순매수":-4762},"개인":{"매도":68788,"매수":75265,"순매수":6478},"기관":{"매도":39756,"매수":38301,"순매수":-1455,"세부":{"금융투자":{"매도":13506,"매수":10828,"순매수":-2679},"투신":{"매도":1447,"매수":1574,"순매수":127},"보험":{"매도":451,"매수":275,"순매수":-177},"사모펀드":{"매도":2769,"매수":1178,"순매수":-1591},"은행":{"매도":10,"매수":79,"순매수":69},"기타금융":{"매도":17,"매수":46,"순매수":29},"연기금등":{"매도":21557,"매수":24322,"순매수":2765},"국가/지자체":{"매도":0,"매수":0,"순매수":0}}},"기타법인":{"매도":1645,"매수":1384,"순매수":-260}},"kosdaq":{"외국인":{"매도":11027,"매수":10845,"순매수":-182},"개인":{"매도":23005,"매수":24891,"순매수":1886},"기관":{"매도":3766,"매수":2098,"순매수":-1669,"세부":{"금융투자":{"매도":2745,"매수":1191,"순매수":-1554},"투신":{"매도":274,"매수":149,"순매수":-126},"보험":{"매도":18,"매수":35,"순매수":17},"사모펀드":{"매도":302,"매수":316,"순매수":14},"은행":{"매도":7,"매수":0,"순매수":-7},"기타금융":{"매도":26,"매수":16,"순매수":-10},"연기금등":{"매도":394,"매수":391,"순매수":-3},"국가/지자체":{"매도":0,"매수":0,"순매수":0}}},"기타법인":{"매도":277,"매수":241,"순매수":-36}},"index":{"kospi":{"지수":9364.13,"전일대비":300.29,"등락률":3.31},"kosdaq":{"지수":982.16,"전일대비":-18.77,"등락률":-1.88}}}