{"ts":"2026-06-11T09:20:01+09:00","kospi":{"외국인":{"매도":24385,"매수":18872,"순매수":-5513},"개인":{"매도":15821,"매수":20906,"순매수":5086},"기관":{"매도":9771,"매수":10005,"순매수":234,"세부":{"금융투자":{"매도":4007,"매수":2221,"순매수":-1786},"투신":{"매도":166,"매수":402,"순매수":237},"보험":{"매도":11,"매수":11,"순매수":0},"사모펀드":{"매도":225,"매수":333,"순매수":108},"은행":{"매도":0,"매수":2,"순매수":2},"기타금융":{"매도":38,"매수":10,"순매수":-29},"연기금등":{"매도":5324,"매수":7025,"순매수":1701},"국가/지자체":{"매도":0,"매수":0,"순매수":0}}},"기타법인":{"매도":221,"매수":414,"순매수":194}},"kosdaq":{"외국인":{"매도":3992,"매수":3085,"순매수":-907},"개인":{"매도":5428,"매수":6250,"순매수":822},"기관":{"매도":489,"매수":540,"순매수":50,"세부":{"금융투자":{"매도":365,"매수":411,"순매수":46},"투신":{"매도":26,"매수":22,"순매수":-5},"보험":{"매도":1,"매수":3,"순매수":2},"사모펀드":{"매도":50,"매수":46,"순매수":-4},"은행":{"매도":0,"매수":0,"순매수":0},"기타금융":{"매도":10,"매수":2,"순매수":-8},"연기금등":{"매도":37,"매수":56,"순매수":19},"국가/지자체":{"매도":0,"매수":0,"순매수":0}}},"기타법인":{"매도":49,"매수":83,"순매수":34}},"index":{"kospi":{"지수":7550.07,"전일대비":-180.75,"등락률":-2.34},"kosdaq":{"지수":933.35,"전일대비":-18.28,"등락률":-1.92}}}