{"ts":"2026-06-10T09:36:00+09:00","kospi":{"외국인":{"매도":36889,"매수":27515,"순매수":-9374},"개인":{"매도":20628,"매수":30437,"순매수":9810},"기관":{"매도":17668,"매수":16947,"순매수":-720,"세부":{"금융투자":{"매도":5857,"매수":4536,"순매수":-1322},"투신":{"매도":167,"매수":555,"순매수":388},"보험":{"매도":9,"매수":38,"순매수":29},"사모펀드":{"매도":194,"매수":751,"순매수":558},"은행":{"매도":3,"매수":7,"순매수":4},"기타금융":{"매도":6,"매수":10,"순매수":4},"연기금등":{"매도":11432,"매수":11050,"순매수":-382},"국가/지자체":{"매도":0,"매수":0,"순매수":0}}},"기타법인":{"매도":328,"매수":612,"순매수":285}},"kosdaq":{"외국인":{"매도":8658,"매수":6935,"순매수":-1723},"개인":{"매도":14127,"매수":15777,"순매수":1650},"기관":{"매도":1523,"매수":1677,"순매수":154,"세부":{"금융투자":{"매도":1150,"매수":949,"순매수":-201},"투신":{"매도":80,"매수":309,"순매수":229},"보험":{"매도":3,"매수":15,"순매수":11},"사모펀드":{"매도":106,"매수":242,"순매수":136},"은행":{"매도":0,"매수":0,"순매수":0},"기타금융":{"매도":74,"매수":3,"순매수":-71},"연기금등":{"매도":111,"매수":160,"순매수":49},"국가/지자체":{"매도":0,"매수":0,"순매수":0}}},"기타법인":{"매도":261,"매수":181,"순매수":-81}}}