{"ts":"2026-06-10T11:00:01+09:00","kospi":{"외국인":{"매도":70591,"매수":50119,"순매수":-20471},"개인":{"매도":42445,"매수":62385,"순매수":19940},"기관":{"매도":41338,"매수":41156,"순매수":-182,"세부":{"금융투자":{"매도":12102,"매수":10548,"순매수":-1554},"투신":{"매도":1258,"매수":2047,"순매수":788},"보험":{"매도":96,"매수":229,"순매수":132},"사모펀드":{"매도":1254,"매수":1865,"순매수":611},"은행":{"매도":46,"매수":36,"순매수":-10},"기타금융":{"매도":11,"매수":35,"순매수":24},"연기금등":{"매도":26570,"매수":26397,"순매수":-173},"국가/지자체":{"매도":0,"매수":0,"순매수":0}}},"기타법인":{"매도":726,"매수":1439,"순매수":713}},"kosdaq":{"외국인":{"매도":16493,"매수":13906,"순매수":-2587},"개인":{"매도":27526,"매수":29669,"순매수":2143},"기관":{"매도":3808,"매수":4298,"순매수":490,"세부":{"금융투자":{"매도":2356,"매수":2042,"순매수":-314},"투신":{"매도":559,"매수":1001,"순매수":442},"보험":{"매도":15,"매수":51,"순매수":36},"사모펀드":{"매도":361,"매수":640,"순매수":279},"은행":{"매도":0,"매수":11,"순매수":11},"기타금융":{"매도":105,"매수":7,"순매수":-98},"연기금등":{"매도":412,"매수":546,"순매수":135},"국가/지자체":{"매도":0,"매수":0,"순매수":0}}},"기타법인":{"매도":501,"매수":455,"순매수":-46}}}