{"ts":"2026-06-10T15:07:01+09:00","kospi":{"외국인":{"매도":143465,"매수":109836,"순매수":-33629},"개인":{"매도":99084,"매수":147949,"순매수":48864},"기관":{"매도":111097,"매수":94107,"순매수":-16990,"세부":{"금융투자":{"매도":37147,"매수":24561,"순매수":-12586},"투신":{"매도":7251,"매수":5931,"순매수":-1320},"보험":{"매도":758,"매수":1160,"순매수":402},"사모펀드":{"매도":5181,"매수":4249,"순매수":-932},"은행":{"매도":61,"매수":97,"순매수":37},"기타금융":{"매도":73,"매수":103,"순매수":30},"연기금등":{"매도":60626,"매수":58005,"순매수":-2621},"국가/지자체":{"매도":0,"매수":0,"순매수":0}}},"기타법인":{"매도":2085,"매수":3840,"순매수":1755}},"kosdaq":{"외국인":{"매도":27765,"매수":27162,"순매수":-603},"개인":{"매도":46048,"매수":47366,"순매수":1319},"기관":{"매도":9855,"매수":9130,"순매수":-725,"세부":{"금융투자":{"매도":4564,"매수":3821,"순매수":-743},"투신":{"매도":2335,"매수":2498,"순매수":163},"보험":{"매도":91,"매수":129,"순매수":38},"사모펀드":{"매도":1385,"매수":1492,"순매수":107},"은행":{"매도":0,"매수":17,"순매수":17},"기타금융":{"매도":131,"매수":19,"순매수":-112},"연기금등":{"매도":1349,"매수":1154,"순매수":-194},"국가/지자체":{"매도":0,"매수":0,"순매수":0}}},"기타법인":{"매도":714,"매수":723,"순매수":9}}}