{"ts":"2026-06-24T09:02:01+09:00","kospi":{"외국인":{"매도":16342,"매수":10532,"순매수":-5810},"개인":{"매도":6673,"매수":10580,"순매수":3907},"기관":{"매도":1522,"매수":3298,"순매수":1776,"세부":{"금융투자":{"매도":318,"매수":1438,"순매수":1120},"투신":{"매도":54,"매수":46,"순매수":-8},"보험":{"매도":8,"매수":6,"순매수":-2},"사모펀드":{"매도":59,"매수":180,"순매수":121},"은행":{"매도":0,"매수":38,"순매수":38},"기타금융":{"매도":0,"매수":0,"순매수":0},"연기금등":{"매도":1083,"매수":1589,"순매수":507},"국가/지자체":{"매도":0,"매수":0,"순매수":0}}},"기타법인":{"매도":68,"매수":196,"순매수":128}},"kosdaq":{"외국인":{"매도":777,"매수":669,"순매수":-109},"개인":{"매도":1155,"매수":970,"순매수":-185},"기관":{"매도":51,"매수":352,"순매수":301,"세부":{"금융투자":{"매도":39,"매수":320,"순매수":281},"투신":{"매도":3,"매수":3,"순매수":0},"보험":{"매도":0,"매수":0,"순매수":0},"사모펀드":{"매도":1,"매수":19,"순매수":18},"은행":{"매도":0,"매수":0,"순매수":0},"기타금융":{"매도":0,"매수":0,"순매수":0},"연기금등":{"매도":8,"매수":10,"순매수":2},"국가/지자체":{"매도":0,"매수":0,"순매수":0}}},"기타법인":{"매도":18,"매수":11,"순매수":-7}},"index":{"kospi":{"지수":8401.58,"전일대비":197.74,"등락률":2.41},"kosdaq":{"지수":900.57,"전일대비":9.05,"등락률":1.02}}}