{"ts":"2026-06-24T10:01:01+09:00","kospi":{"외국인":{"매도":62137,"매수":54417,"순매수":-7720},"개인":{"매도":60090,"매수":67862,"순매수":7772},"기관":{"매도":43175,"매수":42536,"순매수":-639,"세부":{"금융투자":{"매도":12125,"매수":11133,"순매수":-991},"투신":{"매도":1046,"매수":1175,"순매수":129},"보험":{"매도":166,"매수":84,"순매수":-82},"사모펀드":{"매도":1438,"매수":965,"순매수":-472},"은행":{"매도":23,"매수":77,"순매수":53},"기타금융":{"매도":32,"매수":47,"순매수":15},"연기금등":{"매도":28344,"매수":29055,"순매수":710},"국가/지자체":{"매도":0,"매수":0,"순매수":0}}},"기타법인":{"매도":1128,"매수":1714,"순매수":586}},"kosdaq":{"외국인":{"매도":8460,"매수":7588,"순매수":-872},"개인":{"매도":12340,"매수":12068,"순매수":-273},"기관":{"매도":2069,"매수":3211,"순매수":1142,"세부":{"금융투자":{"매도":1497,"매수":2481,"순매수":983},"투신":{"매도":98,"매수":117,"순매수":19},"보험":{"매도":5,"매수":14,"순매수":8},"사모펀드":{"매도":152,"매수":213,"순매수":61},"은행":{"매도":0,"매수":1,"순매수":1},"기타금융":{"매도":1,"매수":0,"순매수":-1},"연기금등":{"매도":315,"매수":386,"순매수":71},"국가/지자체":{"매도":0,"매수":0,"순매수":0}}},"기타법인":{"매도":169,"매수":171,"순매수":3}},"index":{"kospi":{"지수":8468.21,"전일대비":264.37,"등락률":3.22},"kosdaq":{"지수":907.95,"전일대비":16.43,"등락률":1.84}}}