{"ts":"2026-06-24T12:10:01+09:00","kospi":{"외국인":{"매도":118362,"매수":91095,"순매수":-27268},"개인":{"매도":105961,"매수":119836,"순매수":13874},"기관":{"매도":82451,"매수":95018,"순매수":12567,"세부":{"금융투자":{"매도":17844,"매수":28110,"순매수":10266},"투신":{"매도":2636,"매수":2572,"순매수":-64},"보험":{"매도":400,"매수":329,"순매수":-71},"사모펀드":{"매도":2855,"매수":2983,"순매수":128},"은행":{"매도":66,"매수":108,"순매수":42},"기타금융":{"매도":49,"매수":78,"순매수":29},"연기금등":{"매도":58601,"매수":60837,"순매수":2236},"국가/지자체":{"매도":0,"매수":0,"순매수":0}}},"기타법인":{"매도":1887,"매수":2713,"순매수":826}},"kosdaq":{"외국인":{"매도":15217,"매수":14546,"순매수":-670},"개인":{"매도":25744,"매수":24096,"순매수":-1648},"기관":{"매도":4330,"매수":6581,"순매수":2251,"세부":{"금융투자":{"매도":2730,"매수":4349,"순매수":1619},"투신":{"매도":395,"매수":477,"순매수":82},"보험":{"매도":30,"매수":47,"순매수":17},"사모펀드":{"매도":500,"매수":831,"순매수":331},"은행":{"매도":1,"매수":5,"순매수":3},"기타금융":{"매도":3,"매수":3,"순매수":0},"연기금등":{"매도":671,"매수":870,"순매수":199},"국가/지자체":{"매도":0,"매수":0,"순매수":0}}},"기타법인":{"매도":317,"매수":384,"순매수":67}},"index":{"kospi":{"지수":8171.19,"전일대비":-32.65,"등락률":-0.4},"kosdaq":{"지수":890.92,"전일대비":-0.6,"등락률":-0.07}}}