{"ts":"2026-06-24T13:07:01+09:00","kospi":{"외국인":{"매도":135992,"매수":102162,"순매수":-33830},"개인":{"매도":121823,"매수":137695,"순매수":15872},"기관":{"매도":97406,"매수":114366,"순매수":16960,"세부":{"금융투자":{"매도":19636,"매수":33537,"순매수":13900},"투신":{"매도":3356,"매수":3163,"순매수":-193},"보험":{"매도":488,"매수":409,"순매수":-79},"사모펀드":{"매도":3355,"매수":3896,"순매수":542},"은행":{"매도":80,"매수":122,"순매수":42},"기타금융":{"매도":55,"매수":84,"순매수":29},"연기금등":{"매도":70435,"매수":73155,"순매수":2720},"국가/지자체":{"매도":0,"매수":0,"순매수":0}}},"기타법인":{"매도":2191,"매수":3189,"순매수":998}},"kosdaq":{"외국인":{"매도":17346,"매수":16637,"순매수":-709},"개인":{"매도":29121,"매수":27211,"순매수":-1910},"기관":{"매도":5181,"매수":7723,"순매수":2542,"세부":{"금융투자":{"매도":3124,"매수":5035,"순매수":1911},"투신":{"매도":550,"매수":621,"순매수":71},"보험":{"매도":41,"매수":60,"순매수":19},"사모펀드":{"매도":645,"매수":974,"순매수":329},"은행":{"매도":2,"매수":5,"순매수":3},"기타금융":{"매도":4,"매수":3,"순매수":0},"연기금등":{"매도":815,"매수":1025,"순매수":210},"국가/지자체":{"매도":0,"매수":0,"순매수":0}}},"기타법인":{"매도":352,"매수":429,"순매수":77}},"index":{"kospi":{"지수":8211.62,"전일대비":7.78,"등락률":0.09},"kosdaq":{"지수":895.29,"전일대비":3.77,"등락률":0.42}}}