{"ts":"2026-06-24T13:34:01+09:00","kospi":{"외국인":{"매도":144912,"매수":108082,"순매수":-36830},"개인":{"매도":126291,"매수":144338,"순매수":18047},"기관":{"매도":104419,"매수":122226,"순매수":17806,"세부":{"금융투자":{"매도":21307,"매수":35755,"순매수":14447},"투신":{"매도":3919,"매수":3504,"순매수":-415},"보험":{"매도":545,"매수":449,"순매수":-95},"사모펀드":{"매도":3750,"매수":4210,"순매수":460},"은행":{"매도":87,"매수":123,"순매수":36},"기타금융":{"매도":59,"매수":87,"순매수":28},"연기금등":{"매도":74753,"매수":78097,"순매수":3344},"국가/지자체":{"매도":0,"매수":0,"순매수":0}}},"기타법인":{"매도":2360,"매수":3336,"순매수":977}},"kosdaq":{"외국인":{"매도":18193,"매수":17544,"순매수":-649},"개인":{"매도":30615,"매수":28600,"순매수":-2015},"기관":{"매도":5577,"매수":8171,"순매수":2594,"세부":{"금융투자":{"매도":3267,"매수":5252,"순매수":1986},"투신":{"매도":634,"매수":685,"순매수":51},"보험":{"매도":46,"매수":64,"순매수":18},"사모펀드":{"매도":732,"매수":1066,"순매수":334},"은행":{"매도":2,"매수":6,"순매수":3},"기타금융":{"매도":4,"매수":4,"순매수":-1},"연기금등":{"매도":892,"매수":1095,"순매수":203},"국가/지자체":{"매도":0,"매수":0,"순매수":0}}},"기타법인":{"매도":381,"매수":451,"순매수":70}},"index":{"kospi":{"지수":8225.78,"전일대비":21.94,"등락률":0.27},"kosdaq":{"지수":892.69,"전일대비":1.17,"등락률":0.13}}}