{"ts":"2026-07-02T10:19:01+09:00","kospi":{"외국인":{"매도":74623,"매수":39980,"순매수":-34644},"개인":{"매도":48538,"매수":76367,"순매수":27829},"기관":{"매도":33175,"매수":39176,"순매수":6001,"세부":{"금융투자":{"매도":6641,"매수":12463,"순매수":5823},"투신":{"매도":1659,"매수":1231,"순매수":-428},"보험":{"매도":220,"매수":342,"순매수":122},"사모펀드":{"매도":1625,"매수":1439,"순매수":-186},"은행":{"매도":104,"매수":34,"순매수":-70},"기타금융":{"매도":18,"매수":122,"순매수":104},"연기금등":{"매도":22908,"매수":23544,"순매수":636},"국가/지자체":{"매도":0,"매수":0,"순매수":0}}},"기타법인":{"매도":1078,"매수":1892,"순매수":814}},"kosdaq":{"외국인":{"매도":10232,"매수":8018,"순매수":-2214},"개인":{"매도":16430,"매수":18355,"순매수":1925},"기관":{"매도":2457,"매수":2659,"순매수":202,"세부":{"금융투자":{"매도":955,"매수":1620,"순매수":664},"투신":{"매도":478,"매수":244,"순매수":-235},"보험":{"매도":22,"매수":33,"순매수":10},"사모펀드":{"매도":418,"매수":278,"순매수":-140},"은행":{"매도":1,"매수":3,"순매수":1},"기타금융":{"매도":3,"매수":5,"순매수":2},"연기금등":{"매도":578,"매수":477,"순매수":-102},"국가/지자체":{"매도":0,"매수":0,"순매수":0}}},"기타법인":{"매도":178,"매수":265,"순매수":87}},"index":{"kospi":{"지수":7935.51,"전일대비":-367.9,"등락률":-4.43},"kosdaq":{"지수":893.4,"전일대비":-35.95,"등락률":-3.87}}}