{"ts":"2026-07-02T10:22:01+09:00","kospi":{"외국인":{"매도":76224,"매수":41049,"순매수":-35175},"개인":{"매도":50186,"매수":78013,"순매수":27827},"기관":{"매도":34347,"매수":40860,"순매수":6514,"세부":{"금융투자":{"매도":6751,"매수":13109,"순매수":6358},"투신":{"매도":1729,"매수":1292,"순매수":-437},"보험":{"매도":235,"매수":360,"순매수":125},"사모펀드":{"매도":1679,"매수":1506,"순매수":-173},"은행":{"매도":105,"매수":35,"순매수":-70},"기타금융":{"매도":19,"매수":129,"순매수":109},"연기금등":{"매도":23829,"매수":24430,"순매수":601},"국가/지자체":{"매도":0,"매수":0,"순매수":0}}},"기타법인":{"매도":1089,"매수":1923,"순매수":834}},"kosdaq":{"외국인":{"매도":10432,"매수":8204,"순매수":-2228},"개인":{"매도":16787,"매수":18758,"순매수":1971},"기관":{"매도":2559,"매수":2733,"순매수":174,"세부":{"금융투자":{"매도":983,"매수":1650,"순매수":667},"투신":{"매도":521,"매수":256,"순매수":-266},"보험":{"매도":24,"매수":34,"순매수":9},"사모펀드":{"매도":435,"매수":295,"순매수":-140},"은행":{"매도":1,"매수":3,"순매수":1},"기타금융":{"매도":3,"매수":5,"순매수":2},"연기금등":{"매도":592,"매수":491,"순매수":-101},"국가/지자체":{"매도":0,"매수":0,"순매수":0}}},"기타법인":{"매도":186,"매수":269,"순매수":84}},"index":{"kospi":{"지수":7940.16,"전일대비":-363.25,"등락률":-4.37},"kosdaq":{"지수":893.64,"전일대비":-35.71,"등락률":-3.84}}}