{"ts":"2026-06-12T10:13:01+09:00","kospi":{"외국인":{"매도":43583,"매수":53716,"순매수":10133},"개인":{"매도":72844,"매수":54705,"순매수":-18139},"기관":{"매도":27415,"매수":36315,"순매수":8901,"세부":{"금융투자":{"매도":9038,"매수":12099,"순매수":3061},"투신":{"매도":1152,"매수":1914,"순매수":762},"보험":{"매도":263,"매수":271,"순매수":9},"사모펀드":{"매도":712,"매수":1748,"순매수":1036},"은행":{"매도":10,"매수":60,"순매수":50},"기타금융":{"매도":14,"매수":25,"순매수":11},"연기금등":{"매도":16226,"매수":20198,"순매수":3972},"국가/지자체":{"매도":0,"매수":0,"순매수":0}}},"기타법인":{"매도":1875,"매수":980,"순매수":-895}},"kosdaq":{"외국인":{"매도":16696,"매수":16017,"순매수":-679},"개인":{"매도":32336,"매수":32915,"순매수":578},"기관":{"매도":4643,"매수":4715,"순매수":71,"세부":{"금융투자":{"매도":3642,"매수":2206,"순매수":-1436},"투신":{"매도":277,"매수":1516,"순매수":1239},"보험":{"매도":8,"매수":77,"순매수":69},"사모펀드":{"매도":364,"매수":440,"순매수":76},"은행":{"매도":2,"매수":3,"순매수":1},"기타금융":{"매도":7,"매수":5,"순매수":-2},"연기금등":{"매도":343,"매수":467,"순매수":125},"국가/지자체":{"매도":0,"매수":0,"순매수":0}}},"기타법인":{"매도":371,"매수":400,"순매수":29}},"index":{"kospi":{"지수":8365.81,"전일대비":601.86,"등락률":7.75},"kosdaq":{"지수":1032.07,"전일대비":35.14,"등락률":3.52}}}