{"ts":"2026-06-12T10:31:01+09:00","kospi":{"외국인":{"매도":49040,"매수":59883,"순매수":10843},"개인":{"매도":83033,"매수":63062,"순매수":-19971},"기관":{"매도":32335,"매수":42627,"순매수":10292,"세부":{"금융투자":{"매도":9900,"매수":14341,"순매수":4441},"투신":{"매도":1561,"매수":2745,"순매수":1184},"보험":{"매도":338,"매수":353,"순매수":16},"사모펀드":{"매도":868,"매수":2023,"순매수":1154},"은행":{"매도":12,"매수":66,"순매수":54},"기타금융":{"매도":14,"매수":30,"순매수":16},"연기금등":{"매도":19641,"매수":23069,"순매수":3428},"국가/지자체":{"매도":0,"매수":0,"순매수":0}}},"기타법인":{"매도":2271,"매수":1107,"순매수":-1164}},"kosdaq":{"외국인":{"매도":19107,"매수":17921,"순매수":-1186},"개인":{"매도":36550,"매수":37268,"순매수":718},"기관":{"매도":5565,"매수":5994,"순매수":430,"세부":{"금융투자":{"매도":4330,"매수":2559,"순매수":-1771},"투신":{"매도":392,"매수":2193,"순매수":1801},"보험":{"매도":11,"매수":90,"순매수":79},"사모펀드":{"매도":424,"매수":568,"순매수":144},"은행":{"매도":2,"매수":3,"순매수":1},"기타금융":{"매도":9,"매수":6,"순매수":-3},"연기금등":{"매도":397,"매수":576,"순매수":178},"국가/지자체":{"매도":0,"매수":0,"순매수":0}}},"기타법인":{"매도":413,"매수":451,"순매수":38}},"index":{"kospi":{"지수":8311.8,"전일대비":547.85,"등락률":7.06},"kosdaq":{"지수":1027.73,"전일대비":30.8,"등락률":3.09}}}