{"ts":"2026-06-12T13:01:01+09:00","kospi":{"외국인":{"매도":83553,"매수":99421,"순매수":15868},"개인":{"매도":133357,"매수":94557,"순매수":-38800},"기관":{"매도":67026,"매수":91535,"순매수":24510,"세부":{"금융투자":{"매도":16459,"매수":29343,"순매수":12883},"투신":{"매도":10664,"매수":17948,"순매수":7284},"보험":{"매도":1336,"매수":1156,"순매수":-180},"사모펀드":{"매도":3699,"매수":5298,"순매수":1599},"은행":{"매도":29,"매수":120,"순매수":92},"기타금융":{"매도":70,"매수":61,"순매수":-8},"연기금등":{"매도":34769,"매수":37609,"순매수":2840},"국가/지자체":{"매도":0,"매수":0,"순매수":0}}},"기타법인":{"매도":3359,"매수":1781,"순매수":-1578}},"kosdaq":{"외국인":{"매도":31368,"매수":28624,"순매수":-2744},"개인":{"매도":58800,"매수":57594,"순매수":-1206},"기관":{"매도":13010,"매수":17005,"순매수":3995,"세부":{"금융투자":{"매도":7990,"매수":4502,"순매수":-3488},"투신":{"매도":3124,"매수":9686,"순매수":6562},"보험":{"매도":59,"매수":163,"순매수":103},"사모펀드":{"매도":1099,"매수":1549,"순매수":451},"은행":{"매도":2,"매수":5,"순매수":3},"기타금융":{"매도":26,"매수":9,"순매수":-17},"연기금등":{"매도":710,"매수":1091,"순매수":381},"국가/지자체":{"매도":0,"매수":0,"순매수":0}}},"기타법인":{"매도":723,"매수":679,"순매수":-45}},"index":{"kospi":{"지수":8397.22,"전일대비":633.27,"등락률":8.16},"kosdaq":{"지수":1043.2,"전일대비":46.27,"등락률":4.64}}}