{"ts":"2026-07-01T12:46:01+09:00","kospi":{"외국인":{"매도":85463,"매수":68912,"순매수":-16551},"개인":{"매도":91902,"매수":107795,"순매수":15893},"기관":{"매도":75009,"매수":75630,"순매수":621,"세부":{"금융투자":{"매도":21694,"매수":17318,"순매수":-4376},"투신":{"매도":5514,"매수":9581,"순매수":4067},"보험":{"매도":550,"매수":725,"순매수":175},"사모펀드":{"매도":3015,"매수":4160,"순매수":1146},"은행":{"매도":82,"매수":86,"순매수":4},"기타금융":{"매도":36,"매수":345,"순매수":309},"연기금등":{"매도":44118,"매수":43415,"순매수":-703},"국가/지자체":{"매도":0,"매수":0,"순매수":0}}},"기타법인":{"매도":1874,"매수":1910,"순매수":36}},"kosdaq":{"외국인":{"매도":22282,"매수":23515,"순매수":1234},"개인":{"매도":48686,"매수":46840,"순매수":-1847},"기관":{"매도":10246,"매수":11129,"순매수":883,"세부":{"금융투자":{"매도":3416,"매수":5730,"순매수":2314},"투신":{"매도":4826,"매수":2298,"순매수":-2529},"보험":{"매도":65,"매수":94,"순매수":28},"사모펀드":{"매도":635,"매수":1418,"순매수":784},"은행":{"매도":4,"매수":3,"순매수":-1},"기타금융":{"매도":14,"매수":3,"순매수":-11},"연기금등":{"매도":1286,"매수":1584,"순매수":298},"국가/지자체":{"매도":0,"매수":0,"순매수":0}}},"기타법인":{"매도":816,"매수":546,"순매수":-270}},"index":{"kospi":{"지수":8374.21,"전일대비":-102.27,"등락률":-1.21},"kosdaq":{"지수":933.32,"전일대비":17.14,"등락률":1.87}}}