{"ts":"2026-06-23T14:22:01+09:00","kospi":{"외국인":{"매도":157825,"매수":112995,"순매수":-44830},"개인":{"매도":158916,"매수":226534,"순매수":67618},"기관":{"매도":146061,"매수":122698,"순매수":-23363,"세부":{"금융투자":{"매도":43063,"매수":27473,"순매수":-15591},"투신":{"매도":6077,"매수":4130,"순매수":-1947},"보험":{"매도":1573,"매수":642,"순매수":-931},"사모펀드":{"매도":7481,"매수":4655,"순매수":-2826},"은행":{"매도":250,"매수":90,"순매수":-160},"기타금융":{"매도":147,"매수":74,"순매수":-73},"연기금등":{"매도":87469,"매수":85634,"순매수":-1835},"국가/지자체":{"매도":0,"매수":0,"순매수":0}}},"기타법인":{"매도":4728,"매수":5303,"순매수":575}},"kosdaq":{"외국인":{"매도":20672,"매수":21169,"순매수":498},"개인":{"매도":41920,"매수":39705,"순매수":-2216},"기관":{"매도":6223,"매수":7905,"순매수":1681,"세부":{"금융투자":{"매도":2686,"매수":5330,"순매수":2644},"투신":{"매도":871,"매수":505,"순매수":-366},"보험":{"매도":90,"매수":62,"순매수":-28},"사모펀드":{"매도":1175,"매수":649,"순매수":-526},"은행":{"매도":9,"매수":3,"순매수":-6},"기타금융":{"매도":12,"매수":3,"순매수":-9},"연기금등":{"매도":1381,"매수":1353,"순매수":-28},"국가/지자체":{"매도":0,"매수":0,"순매수":0}}},"기타법인":{"매도":493,"매수":530,"순매수":36}},"index":{"kospi":{"지수":8459.37,"전일대비":-655.18,"등락률":-7.19},"kosdaq":{"지수":907.25,"전일대비":-61.15,"등락률":-6.31}}}