{"ts":"2026-06-09T09:37:00+09:00","kospi":{"외국인":{"매도":39064,"매수":34471,"순매수":-4593},"개인":{"매도":36623,"매수":41898,"순매수":5275},"기관":{"매도":17881,"매수":17117,"순매수":-764,"세부":{"금융투자":{"매도":5591,"매수":4225,"순매수":-1366},"투신":{"매도":518,"매수":821,"순매수":303},"보험":{"매도":47,"매수":95,"순매수":48},"사모펀드":{"매도":648,"매수":446,"순매수":-203},"은행":{"매도":5,"매수":37,"순매수":31},"기타금융":{"매도":12,"매수":6,"순매수":-7},"연기금등":{"매도":11059,"매수":11488,"순매수":429},"국가/지자체":{"매도":0,"매수":0,"순매수":0}}},"기타법인":{"매도":724,"매수":806,"순매수":81}},"kosdaq":{"외국인":{"매도":9355,"매수":9976,"순매수":621},"개인":{"매도":17938,"매수":17257,"순매수":-680},"기관":{"매도":1687,"매수":1728,"순매수":41,"세부":{"금융투자":{"매도":1363,"매수":992,"순매수":-371},"투신":{"매도":63,"매수":217,"순매수":154},"보험":{"매도":8,"매수":9,"순매수":1},"사모펀드":{"매도":97,"매수":305,"순매수":208},"은행":{"매도":1,"매수":0,"순매수":-1},"기타금융":{"매도":4,"매수":3,"순매수":-1},"연기금등":{"매도":151,"매수":202,"순매수":51},"국가/지자체":{"매도":0,"매수":0,"순매수":0}}},"기타법인":{"매도":185,"매수":203,"순매수":18}}}