{"ts":"2026-06-09T11:46:00+09:00","kospi":{"외국인":{"매도":84428,"매수":77396,"순매수":-7032},"개인":{"매도":82533,"매수":86702,"순매수":4169},"기관":{"매도":52714,"매수":55014,"순매수":2300,"세부":{"금융투자":{"매도":13261,"매수":15806,"순매수":2545},"투신":{"매도":2375,"매수":2684,"순매수":309},"보험":{"매도":512,"매수":414,"순매수":-97},"사모펀드":{"매도":2953,"매수":1598,"순매수":-1355},"은행":{"매도":35,"매수":113,"순매수":77},"기타금융":{"매도":41,"매수":65,"순매수":24},"연기금등":{"매도":33537,"매수":34334,"순매수":797},"국가/지자체":{"매도":0,"매수":0,"순매수":0}}},"기타법인":{"매도":1825,"매수":2389,"순매수":563}},"kosdaq":{"외국인":{"매도":20498,"매수":21885,"순매수":1387},"개인":{"매도":38510,"매수":35303,"순매수":-3207},"기관":{"매도":4605,"매수":6416,"순매수":1811,"세부":{"금융투자":{"매도":2950,"매수":3590,"순매수":640},"투신":{"매도":525,"매수":856,"순매수":331},"보험":{"매도":44,"매수":42,"순매수":-2},"사모펀드":{"매도":449,"매수":984,"순매수":535},"은행":{"매도":4,"매수":5,"순매수":1},"기타금융":{"매도":13,"매수":13,"순매수":1},"연기금등":{"매도":620,"매수":925,"순매수":305},"국가/지자체":{"매도":0,"매수":0,"순매수":0}}},"기타법인":{"매도":432,"매수":441,"순매수":9}}}