{"ts":"2026-06-26T12:28:01+09:00","kospi":{"외국인":{"매도":101119,"매수":70196,"순매수":-30923},"개인":{"매도":92268,"매수":129922,"순매수":37654},"기관":{"매도":75605,"매수":68284,"순매수":-7321,"세부":{"금융투자":{"매도":19311,"매수":14532,"순매수":-4779},"투신":{"매도":1799,"매수":1453,"순매수":-346},"보험":{"매도":537,"매수":332,"순매수":-205},"사모펀드":{"매도":2105,"매수":1658,"순매수":-448},"은행":{"매도":53,"매수":38,"순매수":-15},"기타금융":{"매도":43,"매수":51,"순매수":8},"연기금등":{"매도":51757,"매수":50220,"순매수":-1537},"국가/지자체":{"매도":0,"매수":0,"순매수":0}}},"기타법인":{"매도":2359,"매수":2949,"순매수":590}},"kosdaq":{"외국인":{"매도":16101,"매수":17504,"순매수":1403},"개인":{"매도":32738,"매수":28519,"순매수":-4218},"기관":{"매도":4371,"매수":7166,"순매수":2795,"세부":{"금융투자":{"매도":2354,"매수":4545,"순매수":2191},"투신":{"매도":382,"매수":787,"순매수":405},"보험":{"매도":54,"매수":86,"순매수":31},"사모펀드":{"매도":669,"매수":768,"순매수":99},"은행":{"매도":1,"매수":1,"순매수":0},"기타금융":{"매도":62,"매수":2,"순매수":-61},"연기금등":{"매도":848,"매수":978,"순매수":130},"국가/지자체":{"매도":0,"매수":0,"순매수":0}}},"기타법인":{"매도":408,"매수":428,"순매수":20}},"index":{"kospi":{"지수":8199.81,"전일대비":-730.49,"등락률":-8.18},"kosdaq":{"지수":842.07,"전일대비":-45.74,"등락률":-5.15}}}