{"ts":"2026-06-30T10:25:01+09:00","kospi":{"외국인":{"매도":59064,"매수":43580,"순매수":-15484},"개인":{"매도":40884,"매수":48731,"순매수":7848},"기관":{"매도":33120,"매수":40439,"순매수":7319,"세부":{"금융투자":{"매도":5593,"매수":10652,"순매수":5059},"투신":{"매도":686,"매수":1893,"순매수":1207},"보험":{"매도":87,"매수":464,"순매수":378},"사모펀드":{"매도":553,"매수":1716,"순매수":1162},"은행":{"매도":80,"매수":12,"순매수":-67},"기타금융":{"매도":8,"매수":23,"순매수":15},"연기금등":{"매도":26114,"매수":25680,"순매수":-434},"국가/지자체":{"매도":0,"매수":0,"순매수":0}}},"기타법인":{"매도":570,"매수":887,"순매수":317}},"kosdaq":{"외국인":{"매도":10702,"매수":8332,"순매수":-2370},"개인":{"매도":18281,"매수":20458,"순매수":2178},"기관":{"매도":3166,"매수":3408,"순매수":242,"세부":{"금융투자":{"매도":1848,"매수":2094,"순매수":247},"투신":{"매도":420,"매수":357,"순매수":-64},"보험":{"매도":15,"매수":40,"순매수":25},"사모펀드":{"매도":460,"매수":458,"순매수":-2},"은행":{"매도":17,"매수":8,"순매수":-9},"기타금융":{"매도":33,"매수":0,"순매수":-32},"연기금등":{"매도":373,"매수":449,"순매수":77},"국가/지자체":{"매도":0,"매수":0,"순매수":0}}},"기타법인":{"매도":264,"매수":214,"순매수":-49}},"index":{"kospi":{"지수":8351.19,"전일대비":-43.46,"등락률":-0.52},"kosdaq":{"지수":917.39,"전일대비":-3.18,"등락률":-0.35}}}