{"ts":"2026-06-25T13:45:01+09:00","kospi":{"외국인":{"매도":122838,"매수":109249,"순매수":-13589},"개인":{"매도":125594,"매수":111927,"순매수":-13667},"기관":{"매도":77666,"매수":104667,"순매수":27001,"세부":{"금융투자":{"매도":13310,"매수":36426,"순매수":23115},"투신":{"매도":3728,"매수":4303,"순매수":575},"보험":{"매도":1082,"매수":444,"순매수":-638},"사모펀드":{"매도":4051,"매수":5210,"순매수":1159},"은행":{"매도":67,"매수":135,"순매수":68},"기타금융":{"매도":56,"매수":67,"순매수":11},"연기금등":{"매도":55371,"매수":58082,"순매수":2711},"국가/지자체":{"매도":0,"매수":0,"순매수":0}}},"기타법인":{"매도":2649,"매수":2904,"순매수":255}},"kosdaq":{"외국인":{"매도":16278,"매수":15102,"순매수":-1176},"개인":{"매도":30399,"매수":33003,"순매수":2604},"기관":{"매도":6667,"매수":5242,"순매수":-1425,"세부":{"금융투자":{"매도":3843,"매수":2283,"순매수":-1560},"투신":{"매도":869,"매수":1171,"순매수":302},"보험":{"매도":69,"매수":105,"순매수":36},"사모펀드":{"매도":1008,"매수":701,"순매수":-307},"은행":{"매도":3,"매수":6,"순매수":3},"기타금융":{"매도":4,"매수":2,"순매수":-2},"연기금등":{"매도":869,"매수":973,"순매수":104},"국가/지자체":{"매도":0,"매수":0,"순매수":0}}},"기타법인":{"매도":442,"매수":438,"순매수":-3}},"index":{"kospi":{"지수":8959.31,"전일대비":488.29,"등락률":5.76},"kosdaq":{"지수":893.5,"전일대비":-15.81,"등락률":-1.74}}}