{"ts":"2026-06-25T14:39:01+09:00","kospi":{"외국인":{"매도":142631,"매수":132327,"순매수":-10303},"개인":{"매도":156273,"매수":132186,"순매수":-24087},"기관":{"매도":93671,"매수":128007,"순매수":34336,"세부":{"금융투자":{"매도":17270,"매수":49071,"순매수":31800},"투신":{"매도":5616,"매수":5371,"순매수":-245},"보험":{"매도":1475,"매수":640,"순매수":-835},"사모펀드":{"매도":5187,"매수":6346,"순매수":1159},"은행":{"매도":85,"매수":137,"순매수":52},"기타금융":{"매도":90,"매수":82,"순매수":-8},"연기금등":{"매도":63948,"매수":66361,"순매수":2413},"국가/지자체":{"매도":0,"매수":0,"순매수":0}}},"기타법인":{"매도":3570,"매수":3624,"순매수":54}},"kosdaq":{"외국인":{"매도":18369,"매수":18053,"순매수":-316},"개인":{"매도":34827,"매수":36739,"순매수":1913},"기관":{"매도":7937,"매수":6335,"순매수":-1602,"세부":{"금융투자":{"매도":4347,"매수":2705,"순매수":-1641},"투신":{"매도":1141,"매수":1442,"순매수":301},"보험":{"매도":102,"매수":134,"순매수":33},"사모펀드":{"매도":1294,"매수":885,"순매수":-408},"은행":{"매도":7,"매수":6,"순매수":-1},"기타금융":{"매도":4,"매수":2,"순매수":-2},"연기금등":{"매도":1043,"매수":1160,"순매수":117},"국가/지자체":{"매도":0,"매수":0,"순매수":0}}},"기타법인":{"매도":490,"매수":496,"순매수":6}},"index":{"kospi":{"지수":9021.74,"전일대비":550.72,"등락률":6.5},"kosdaq":{"지수":891.56,"전일대비":-17.75,"등락률":-1.95}}}