{"ts":"2026-06-25T15:04:01+09:00","kospi":{"외국인":{"매도":154699,"매수":148394,"순매수":-6306},"개인":{"매도":170752,"매수":143650,"순매수":-27102},"기관":{"매도":105313,"매수":139043,"순매수":33730,"세부":{"금융투자":{"매도":21619,"매수":54195,"순매수":32576},"투신":{"매도":6803,"매수":6575,"순매수":-227},"보험":{"매도":1725,"매수":805,"순매수":-920},"사모펀드":{"매도":5688,"매수":7227,"순매수":1539},"은행":{"매도":92,"매수":138,"순매수":45},"기타금융":{"매도":98,"매수":91,"순매수":-8},"연기금등":{"매도":69287,"매수":70013,"순매수":725},"국가/지자체":{"매도":0,"매수":0,"순매수":0}}},"기타법인":{"매도":4347,"매수":4025,"순매수":-323}},"kosdaq":{"외국인":{"매도":19649,"매수":19615,"순매수":-34},"개인":{"매도":36851,"매수":38527,"순매수":1676},"기관":{"매도":8800,"매수":7158,"순매수":-1642,"세부":{"금융투자":{"매도":4682,"매수":3014,"순매수":-1668},"투신":{"매도":1346,"매수":1713,"순매수":367},"보험":{"매도":131,"매수":150,"순매수":19},"사모펀드":{"매도":1490,"매수":980,"순매수":-510},"은행":{"매도":7,"매수":6,"순매수":-1},"기타금융":{"매도":5,"매수":2,"순매수":-2},"연기금등":{"매도":1140,"매수":1293,"순매수":153},"국가/지자체":{"매도":0,"매수":0,"순매수":0}}},"기타법인":{"매도":530,"매수":531,"순매수":0}},"index":{"kospi":{"지수":8993.16,"전일대비":522.14,"등락률":6.16},"kosdaq":{"지수":889.44,"전일대비":-19.87,"등락률":-2.19}}}