{"ts":"2026-06-08T13:25:00+09:00","kospi":{"외국인":{"매도":116159,"매수":103789,"순매수":-12370},"개인":{"매도":125949,"매수":135435,"순매수":9486},"기관":{"매도":82079,"매수":83450,"순매수":1372,"세부":{"금융투자":{"매도":25744,"매수":24619,"순매수":-1125},"투신":{"매도":2798,"매수":3941,"순매수":1143},"보험":{"매도":560,"매수":754,"순매수":194},"사모펀드":{"매도":3760,"매수":4668,"순매수":908},"은행":{"매도":278,"매수":236,"순매수":-42},"기타금융":{"매도":26,"매수":126,"순매수":100},"연기금등":{"매도":48913,"매수":49106,"순매수":193},"국가/지자체":{"매도":0,"매수":0,"순매수":0}}},"기타법인":{"매도":2206,"매수":3718,"순매수":1512}},"kosdaq":{"외국인":{"매도":21243,"매수":21037,"순매수":-205},"개인":{"매도":38197,"매수":38111,"순매수":-87},"기관":{"매도":5513,"매수":6107,"순매수":594,"세부":{"금융투자":{"매도":2743,"매수":4192,"순매수":1448},"투신":{"매도":933,"매수":629,"순매수":-304},"보험":{"매도":63,"매수":30,"순매수":-33},"사모펀드":{"매도":864,"매수":820,"순매수":-43},"은행":{"매도":23,"매수":4,"순매수":-19},"기타금융":{"매도":195,"매수":12,"순매수":-183},"연기금등":{"매도":691,"매수":419,"순매수":-272},"국가/지자체":{"매도":0,"매수":0,"순매수":0}}},"기타법인":{"매도":825,"매수":523,"순매수":-302}}}