{"ts":"2026-06-18T12:58:01+09:00","kospi":{"외국인":{"매도":95507,"매수":88336,"순매수":-7171},"개인":{"매도":123627,"매수":130636,"순매수":7009},"기관":{"매도":72918,"매수":73833,"순매수":915,"세부":{"금융투자":{"매도":18792,"매수":17667,"순매수":-1126},"투신":{"매도":3849,"매수":3550,"순매수":-299},"보험":{"매도":535,"매수":396,"순매수":-139},"사모펀드":{"매도":5283,"매수":3778,"순매수":-1505},"은행":{"매도":44,"매수":87,"순매수":43},"기타금융":{"매도":52,"매수":44,"순매수":-8},"연기금등":{"매도":44362,"매수":48311,"순매수":3949},"국가/지자체":{"매도":0,"매수":0,"순매수":0}}},"기타법인":{"매도":3189,"매수":2436,"순매수":-753}},"kosdaq":{"외국인":{"매도":17038,"매수":14556,"순매수":-2482},"개인":{"매도":34991,"매수":38915,"순매수":3925},"기관":{"매도":4946,"매수":3506,"순매수":-1440,"세부":{"금융투자":{"매도":2997,"매수":1732,"순매수":-1265},"투신":{"매도":593,"매수":615,"순매수":22},"보험":{"매도":60,"매수":41,"순매수":-19},"사모펀드":{"매도":647,"매수":512,"순매수":-135},"은행":{"매도":9,"매수":0,"순매수":-9},"기타금융":{"매도":29,"매수":16,"순매수":-12},"연기금등":{"매도":611,"매수":589,"순매수":-22},"국가/지자체":{"매도":0,"매수":0,"순매수":0}}},"기타법인":{"매도":415,"매수":412,"순매수":-3}},"index":{"kospi":{"지수":8995.57,"전일대비":131.33,"등락률":1.48},"kosdaq":{"지수":999.2,"전일대비":-32.76,"등락률":-3.17}}}