{"ts":"2026-06-29T12:46:01+09:00","kospi":{"외국인":{"매도":121482,"매수":70964,"순매수":-50517},"개인":{"매도":60461,"매수":97470,"순매수":37008},"기관":{"매도":67168,"매수":79154,"순매수":11986,"세부":{"금융투자":{"매도":11545,"매수":20861,"순매수":9316},"투신":{"매도":3179,"매수":3668,"순매수":489},"보험":{"매도":355,"매수":349,"순매수":-5},"사모펀드":{"매도":2215,"매수":2607,"순매수":392},"은행":{"매도":81,"매수":14,"순매수":-67},"기타금융":{"매도":45,"매수":45,"순매수":0},"연기금등":{"매도":49747,"매수":51609,"순매수":1861},"국가/지자체":{"매도":0,"매수":0,"순매수":0}}},"기타법인":{"매도":1065,"매수":2588,"순매수":1523}},"kosdaq":{"외국인":{"매도":17537,"매수":17146,"순매수":-391},"개인":{"매도":31849,"매수":28135,"순매수":-3714},"기관":{"매도":5809,"매수":9948,"순매수":4139,"세부":{"금융투자":{"매도":2567,"매수":6003,"순매수":3437},"투신":{"매도":1386,"매수":1285,"순매수":-102},"보험":{"매도":79,"매수":118,"순매수":39},"사모펀드":{"매도":777,"매수":1208,"순매수":430},"은행":{"매도":10,"매수":3,"순매수":-7},"기타금융":{"매도":10,"매수":9,"순매수":-1},"연기금등":{"매도":980,"매수":1322,"순매수":343},"국가/지자체":{"매도":0,"매수":0,"순매수":0}}},"기타법인":{"매도":403,"매수":368,"순매수":-35}},"index":{"kospi":{"지수":8208.85,"전일대비":-202.36,"등락률":-2.41},"kosdaq":{"지수":907.15,"전일대비":55.78,"등락률":6.55}}}